MANIFEST.in
setup.py
cbr/__init__.py
cbr/admin.py
cbr/apps.py
cbr/models.py
cbr/locale/ru/LC_MESSAGES/django.mo
cbr/locale/ru/LC_MESSAGES/django.po
cbr/management/__init__.py
cbr/management/__pycache__/__init__.cpython-35.pyc
cbr/management/commands/__init__.py
cbr/management/commands/load_cbr.py
cbr/management/commands/__pycache__/__init__.cpython-35.pyc
cbr/management/commands/__pycache__/load_cbr.cpython-35.pyc
cbr/migrations/0001_initial.py
cbr/migrations/0002_cbrcurrencyrate_change.py
cbr/migrations/__init__.py
cbr/migrations/__pycache__/0001_initial.cpython-35.pyc
cbr/migrations/__pycache__/0002_cbrcurrencyrate_change.cpython-35.pyc
cbr/migrations/__pycache__/__init__.cpython-35.pyc
cbr/templates/cbr/informer.html
cbr/templatetags/__init__.py
cbr/templatetags/cbr.py
cbr/templatetags/__pycache__/__init__.cpython-35.pyc
cbr/templatetags/__pycache__/cbr.cpython-35.pyc
django_cbr.egg-info/PKG-INFO
django_cbr.egg-info/SOURCES.txt
django_cbr.egg-info/dependency_links.txt
django_cbr.egg-info/not-zip-safe
django_cbr.egg-info/requires.txt
django_cbr.egg-info/top_level.txt